Workerpy/Manager.py
Workerpy/NatsBase.py
Workerpy/RequestAgent.py
Workerpy/__init__.py
Workerpy/agent.py
Workerpy/kafkaBase.py
Workerpy/loggs.py
Workerpy/options.py
Workerpy-1.1.0.dist-info/METADATA
Workerpy-1.1.0.dist-info/WHEEL
Workerpy-1.1.0.dist-info/top_level.txt
Workerpy-1.1.0.dist-info/RECORD
