Metadata-Version: 2.1
Name: Workerpy
Version: 1.1.0
Summary: Libreria para crear Workers que responden a eventos desde kafka/Nats
Home-page: UNKNOWN
Author: Enoi Barrera Guzman
Author-email: zafiro3000x@gmail.com
License: UNKNOWN
Platform: UNKNOWN
Classifier: Programming Language :: Python :: 3
Requires-Dist: kafka-python (==1.4.6)
Requires-Dist: Logbook (==1.4.3)
Requires-Dist: asyncio-nats-client (==0.9.2)
Requires-Dist: python-dotenv (==0.10.3)
